Metadata-Version: 2.1
Name: Keras-JukeBox
Version: 0.0.1
Summary: A UI based callback for tf-keras
Home-page: https://github.com/pk00095/keras_JukeBox.git
Author: T Pratik
Author-email: pk00095@gmail.com
License: UNKNOWN
Platform: UNKNOWN
Classifier: Programming Language :: Python :: 3
Classifier: License :: OSI Approved :: MIT License
Classifier: Operating System :: POSIX :: Linux
Requires-Python: >=3.6
